{
    "ticker1": {
        "stock_ticker": "ASTI",
        "benchmark_ticker": "VTI",
        "greater_than": 0.015,
        "less_than": 0.05
    },
    "ticker2": {
        "stock_ticker": "EQ",
        "benchmark_ticker": "VTV",
        "greater_than": 0.015,
        "less_than": 0.04
    },
    "ticker3": {
        "stock_ticker": "IONR",
        "benchmark_ticker": "IWM",
        "greater_than": 0.01,
        "less_than": 0.035
    },
    "ticker4": {
        "stock_ticker": "ELPW",
        "benchmark_ticker": "VTV",
        "greater_than": 0.025,
        "less_than": 0.04
    },
    "ticker5": {
        "stock_ticker": "KALA",
        "benchmark_ticker": "IWM",
        "greater_than": 0.02,
        "less_than": 0.03
    },
    "ticker6": {
        "stock_ticker": "HOVR",
        "benchmark_ticker": "TLT",
        "greater_than": 0.025,
        "less_than": 0.045
    },
    "ticker7": {
        "stock_ticker": "IMCC",
        "benchmark_ticker": "XLF",
        "greater_than": 0.015,
        "less_than": 0.03
    },
    "ticker8": {
        "stock_ticker": "HUBC",
        "benchmark_ticker": "XLK",
        "greater_than": 0.015,
        "less_than": 0.045
    },
    "ticker9": {
        "stock_ticker": "AXTI",
        "benchmark_ticker": "IWM",
        "greater_than": 0.03,
        "less_than": 0.045
    },
    "ticker10": {
        "stock_ticker": "KXIN",
        "benchmark_ticker": "IWM",
        "greater_than": 0.0,
        "less_than": 0.045
    },
    "ticker11": {
        "stock_ticker": "ELWS",
        "benchmark_ticker": "VTI",
        "greater_than": 0.0,
        "less_than": 0.015
    },
    "ticker12": {
        "stock_ticker": "ALAB",
        "benchmark_ticker": "VTI",
        "greater_than": 0.0,
        "less_than": 0.045
    },
    "ticker13": {
        "stock_ticker": "RCAT",
        "benchmark_ticker": "XLK",
        "greater_than": 0.03,
        "less_than": 0.045
    },
    "ticker14": {
        "stock_ticker": "AISP",
        "benchmark_ticker": "XLV",
        "greater_than": 0.01,
        "less_than": 0.03
    },
    "ticker15": {
        "stock_ticker": "PGEN",
        "benchmark_ticker": "XLV",
        "greater_than": 0.005,
        "less_than": 0.04
    },
    "ticker16": {
        "stock_ticker": "XERS",
        "benchmark_ticker": "TLT",
        "greater_than": 0.0,
        "less_than": 0.035
    },
    "ticker17": {
        "stock_ticker": "CING",
        "benchmark_ticker": "XLE",
        "greater_than": 0.0,
        "less_than": 0.035
    },
    "ticker18": {
        "stock_ticker": "AMR",
        "benchmark_ticker": "IWM",
        "greater_than": 0.01,
        "less_than": 0.025
    },
    "ticker19": {
        "stock_ticker": "PRLD",
        "benchmark_ticker": "IWM",
        "greater_than": 0.02,
        "less_than": 0.04
    },
    "ticker20": {
        "stock_ticker": "SIFY",
        "benchmark_ticker": "VTV",
        "greater_than": 0.0,
        "less_than": 0.02
    },
    "ticker21": {
        "stock_ticker": "JZXN",
        "benchmark_ticker": "XLK",
        "greater_than": 0.015,
        "less_than": 0.035
    },
    "ticker22": {
        "stock_ticker": "LWLG",
        "benchmark_ticker": "VB",
        "greater_than": 0.0,
        "less_than": 0.025
    },
    "ticker23": {
        "stock_ticker": "ZURA",
        "benchmark_ticker": "XLK",
        "greater_than": 0.005,
        "less_than": 0.015
    },
    "ticker24": {
        "stock_ticker": "SGML",
        "benchmark_ticker": "VTI",
        "greater_than": 0.0,
        "less_than": 0.015
    },
    "ticker25": {
        "stock_ticker": "TROO",
        "benchmark_ticker": "VTV",
        "greater_than": 0.0,
        "less_than": 0.045
    },
    "ticker26": {
        "stock_ticker": "RGNX",
        "benchmark_ticker": "XLK",
        "greater_than": 0.005,
        "less_than": 0.045
    },
    "ticker27": {
        "stock_ticker": "OPTX",
        "benchmark_ticker": "XLV",
        "greater_than": 0.025,
        "less_than": 0.045
    },
    "ticker28": {
        "stock_ticker": "MTVA",
        "benchmark_ticker": "XLK",
        "greater_than": 0.0,
        "less_than": 0.015
    },
    "ticker29": {
        "stock_ticker": "KSCP",
        "benchmark_ticker": "XLK",
        "greater_than": 0.005,
        "less_than": 0.04
    },
    "ticker30": {
        "stock_ticker": "FTHM",
        "benchmark_ticker": "IWM",
        "greater_than": 0.01,
        "less_than": 0.02
    }
}